pynodal/.ipynb_checkpoints/dev-checkpoint.ipynb
pynodal/__init__.py
pynodal/dev.ipynb
pynodal/ipr.py
pynodal/jupyterlog
pynodal-0.1.0.dist-info/WHEEL
pynodal-0.1.0.dist-info/METADATA
pynodal-0.1.0.dist-info/RECORD
