Metadata-Version: 2.1
Name: pynodal
Version: 0.1.0
Summary: 
Author: Mariana Vasconcelos
Author-email: mari.aspennl@gmail.com
Requires-Python: >=3.10,<4.0
Classifier: Programming Language :: Python :: 3
Classifier: Programming Language :: Python :: 3.10
Requires-Dist: matplotlib (>=3.5.2,<4.0.0)
Requires-Dist: pandas (>=1.4.3,<2.0.0)
